jupyter_matlab_kernel/README.md
jupyter_matlab_kernel/__init__.py
jupyter_matlab_kernel/__main__.py
jupyter_matlab_kernel/base_kernel.py
jupyter_matlab_kernel/jsp_kernel.py
jupyter_matlab_kernel/kernel_factory.py
jupyter_matlab_kernel/kernelspec.py
jupyter_matlab_kernel/magic_execution_engine.py
jupyter_matlab_kernel/magic_helper.py
jupyter_matlab_kernel/mpm_kernel.py
jupyter_matlab_kernel/mwi_comm_helpers.py
jupyter_matlab_kernel/mwi_exceptions.py
jupyter_matlab_kernel/mwi_logger.py
jupyter_matlab_kernel/test_utils.py
jupyter_matlab_kernel/comms/__init__.py
jupyter_matlab_kernel/comms/labextension/__init__.py
jupyter_matlab_kernel/comms/labextension/labextension.py
jupyter_matlab_kernel/kernelspec/logo-64x64.png
jupyter_matlab_kernel/kernelspec/logo-svg.svg
jupyter_matlab_kernel/magics/README.md
jupyter_matlab_kernel/magics/file.py
jupyter_matlab_kernel/magics/help.py
jupyter_matlab_kernel/magics/lsmagic.py
jupyter_matlab_kernel/magics/matlab.py
jupyter_matlab_kernel/magics/time.py
jupyter_matlab_kernel/magics/base/matlab_magic.py
jupyter_matlab_kernel/matlab/processJupyterKernelRequest.m
jupyter_matlab_kernel/matlab/+jupyter/Idler.m
jupyter_matlab_kernel/matlab/+jupyter/complete.m
jupyter_matlab_kernel/matlab/+jupyter/execute.m
jupyter_matlab_kernel/matlab/+jupyter/getOrStashExceptions.m
jupyter_matlab_kernel/matlab/+jupyter/shutdown.m
jupyter_matlab_proxy/README.md
jupyter_matlab_proxy/__init__.py
jupyter_matlab_proxy/icon_open_matlab.svg
jupyter_matlab_proxy/jupyter_config.py
jupyter_matlab_proxy-0.18.0.data/data/share/jupyter/kernels/jupyter_matlab_kernel/kernel.json
jupyter_matlab_proxy-0.18.0.data/data/share/jupyter/kernels/jupyter_matlab_kernel/logo-64x64.png
jupyter_matlab_proxy-0.18.0.data/data/share/jupyter/kernels/jupyter_matlab_kernel/logo-svg.svg
jupyter_matlab_proxy-0.18.0.data/data/share/jupyter/labextensions/jupyter_matlab_labextension/package.json
jupyter_matlab_proxy-0.18.0.dist-info/METADATA
jupyter_matlab_proxy-0.18.0.dist-info/WHEEL
jupyter_matlab_proxy-0.18.0.dist-info/entry_points.txt
jupyter_matlab_proxy-0.18.0.dist-info/licenses/LICENSE.md
jupyter_matlab_proxy-0.18.0.dist-info/RECORD
