Metadata-Version: 2.4
Name: jupyter-matlab-proxy
Version: 0.18.0
Summary: MATLAB Integration for Jupyter
Project-URL: Homepage, https://github.com/mathworks/jupyter-matlab-proxy
Author-email: "The MathWorks Inc." <jupyter-support@mathworks.com>
License: MATHWORKS CLOUD REFERENCE ARCHITECTURE LICENSE
License-File: LICENSE.md
Keywords: Jupyter,Jupyter Proxy,Jupyter Server Proxy,JupyterLab,MATLAB,MATLAB Integration for Jupyter,MATLAB Kernel for Jupyter,MATLAB Proxy,MATLAB Web Desktop,Remote MATLAB Web Access
Classifier: Framework :: Jupyter
Classifier: Framework :: Jupyter :: JupyterLab
Classifier: Intended Audience :: Developers
Classifier: Natural Language :: English
Classifier: Programming Language :: Python
Classifier: Programming Language :: Python :: 3.8
Classifier: Programming Language :: Python :: 3.9
Classifier: Programming Language :: Python :: 3.10
Classifier: Programming Language :: Python :: 3.11
Requires-Python: <3.14,>=3.10
Requires-Dist: aiohttp
Requires-Dist: ipykernel>=6.0.3
Requires-Dist: jupyter-client
Requires-Dist: jupyter-server-proxy>=4.1.0
Requires-Dist: matlab-proxy>=0.30.0
Requires-Dist: psutil
Requires-Dist: requests
Provides-Extra: dev
Requires-Dist: black; extra == 'dev'
Requires-Dist: jupyter-kernel-test; extra == 'dev'
Requires-Dist: pytest; extra == 'dev'
Requires-Dist: pytest-aiohttp; extra == 'dev'
Requires-Dist: pytest-asyncio; extra == 'dev'
Requires-Dist: pytest-cov; extra == 'dev'
Requires-Dist: pytest-mock; extra == 'dev'
Requires-Dist: pytest-playwright; extra == 'dev'
